main.py
zendesk_cli-0.0.0.dist-info/METADATA
zendesk_cli-0.0.0.dist-info/WHEEL
zendesk_cli-0.0.0.dist-info/top_level.txt
zendesk_cli-0.0.0.dist-info/RECORD
