Metadata-Version: 2.4
Name: zendesk-cli
Version: 0.0.0
Summary: Coming soon
Requires-Python: >=3.12
